aindex_diy/__init__.py
aindex_diy/aindex.py
aindex_diy-0.1.0.dist-info/METADATA
aindex_diy-0.1.0.dist-info/WHEEL
aindex_diy-0.1.0.dist-info/licenses/LICENSE
aindex_diy-0.1.0.dist-info/RECORD
