Metadata-Version: 2.4
Name: aindex-diy
Version: 0.1.0
Summary: AI Agent Index - Route queries to the right AI agent. DIY framework for building your own agent registry.
Project-URL: Homepage, https://humotica.com
Project-URL: Repository, https://github.com/humoticaos/aindex-diy
Author-email: HumoticaOS <info@humotica.com>
License-Expression: MIT
License-File: LICENSE
Keywords: agents,ai,index,llm,multi-agent,routing
Classifier: Development Status :: 4 - Beta
Classifier: Intended Audience :: Developers
Classifier: License :: OSI Approved :: MIT License
Classifier: Programming Language :: Python :: 3
Classifier: Programming Language :: Python :: 3.9
Classifier: Programming Language :: Python :: 3.10
Classifier: Programming Language :: Python :: 3.11
Classifier: Programming Language :: Python :: 3.12
Classifier: Topic :: Scientific/Engineering :: Artificial Intelligence
Requires-Python: >=3.9
